{
    "teams": {
        "1": {
            "id": 1,
            "name": "Australia",
            "contact": "Pietro Boyle",
            "email": "Imelda_Heidenreich@yahoo.com",
            "events": {
                "basketball": [
                    "Jess Koelpin"
                ],
                "typing": [
                    "Wilhelm Goldner"
                ],
                "jump": [
                    "Bartholome Donnelly"
                ],
                "airplane": [
                    "Nick Sanford"
                ],
                "skeleton": [
                    "Mckenzie Hamill"
                ],
                "biathalon": [
                    "Rahul Wehner"
                ],
                "balloon": [
                    "Raymond Johnston"
                ],
                "curling": [
                    "Wilhelmine Zieme"
                ]
            }
        },
        "2": {
            "id": 2,
            "name": "Germany",
            "contact": "Adrienne Hoeger",
            "email": "Keyon_Purdy@yahoo.com",
            "events": {
                "basketball": [
                    "Reed Labadie"
                ],
                "typing": [
                    "Kristy Schroeder"
                ],
                "jump": [
                    "Vesta Hessel"
                ],
                "airplane": [
                    "Edna Cronin"
                ],
                "skeleton": [
                    "Laurianne Stehr"
                ],
                "biathalon": [
                    "Jamal Gusikowski"
                ],
                "balloon": [
                    "Giovani Volkman"
                ],
                "curling": [
                    "Dariana Cartwright"
                ]
            }
        },
        "3": {
            "id": 3,
            "name": "Russia",
            "contact": "Tyrel Lowe",
            "email": "Lennie_Torphy96@hotmail.com",
            "events": {
                "basketball": [
                    "Laney Osinski"
                ],
                "typing": [
                    "Brandyn Wolff"
                ],
                "jump": [
                    "Kiera Altenwerth"
                ],
                "airplane": [
                    "Humberto Kohler"
                ],
                "skeleton": [
                    "Pat Collier"
                ],
                "biathalon": [
                    "Marilyne Homenick"
                ],
                "balloon": [
                    "Rosario Braun"
                ],
                "curling": [
                    "Lavinia Durgan"
                ]
            }
        },
        "4": {
            "id": 4,
            "name": "India ",
            "contact": "Margaret Lueilwitz",
            "email": "Benedict_Thompson78@gmail.com",
            "events": {
                "basketball": [
                    "Laurie Pfeffer"
                ],
                "typing": [
                    "Sarai Will"
                ],
                "jump": [
                    "Vernice Boehm"
                ],
                "airplane": [
                    "Jack Predovic"
                ],
                "skeleton": [
                    "Aaliyah Jones"
                ],
                "biathalon": [
                    "Trudie Hermann"
                ],
                "balloon": [
                    "Maia Bashirian"
                ],
                "curling": [
                    "Lloyd Lockman"
                ]
            }
        },
        "5": {
            "id": 5,
            "name": "Norway",
            "contact": "Pearline Jaskolski",
            "email": "Eliseo.Feeney@yahoo.com",
            "events": {
                "basketball": [
                    "Myrtis Pacocha"
                ],
                "typing": [
                    "Elena Fritsch"
                ],
                "jump": [
                    "Floyd Gaylord"
                ],
                "airplane": [
                    "Gerson Monahan"
                ],
                "skeleton": [
                    "Karson Abshire"
                ],
                "biathalon": [
                    "Orie Purdy"
                ],
                "balloon": [
                    "Isadore O'Reilly"
                ],
                "curling": [
                    "Wilton Jenkins"
                ]
            }
        }
    },
    "events": {
        "basketball": {
            "name": "Trashcan Basketball",
            "description": "Sample Description",
            "location": "Sample Location",
            "time": "12pm",
            "results": {}
        },
        "typing": {
            "name": "Finger Skating",
            "description": "Sample Description",
            "location": "Sample Location",
            "time": "12pm",
            "results": {}
        },
        "jump": {
            "name": "Long Jump",
            "description": "Sample Description",
            "location": "Sample Location",
            "time": "12pm",
            "results": {}
        },
        "airplane": {
            "name": "Paper Airplane Javelin",
            "description": "Sample Description",
            "location": "Sample Location",
            "time": "12pm",
            "results": {}
        },
        "skeleton": {
            "name": "Skeleton",
            "description": "Sample Description",
            "location": "Sample Location",
            "time": "12pm",
            "results": {}
        },
        "biathalon": {
            "name": "Biathlon",
            "description": "Sample Description",
            "location": "Sample Location",
            "time": "12pm",
            "results": {}
        },
        "balloon": {
            "name": "Balloon Dash",
            "description": "Sample Description",
            "location": "Sample Location",
            "time": "12pm",
            "results": {}
        },
        "curling": {
            "name": "Chair Curling",
            "description": "Sample Description",
            "location": "Sample Location",
            "time": "12pm",
            "results": {}
        }
    }
}
